{
  "source": "douyin",
  "title": "抖音热点",
  "updated_at": "2026-06-29T14:57:16+00:00",
  "fetch_ok": true,
  "items": [
    {
      "rank": 1,
      "title": "用一篇长文记录毕业季",
      "url": "https://www.douyin.com/hot/2551265",
      "hot": "12054185"
    },
    {
      "rank": 2,
      "title": "和平精英夏日探险派对",
      "url": "https://www.douyin.com/hot/2551808",
      "hot": "11916499"
    },
    {
      "rank": 3,
      "title": "教育发展“十五五”规划",
      "url": "https://www.douyin.com/hot/2552261",
      "hot": "11916392"
    },
    {
      "rank": 4,
      "title": "Steam夏促攻略来了",
      "url": "https://www.douyin.com/hot/2552327",
      "hot": "11500116"
    },
    {
      "rank": 5,
      "title": "高考志愿填报专业怎么选",
      "url": "https://www.douyin.com/hot/2551262",
      "hot": "10748061"
    },
    {
      "rank": 6,
      "title": "网警提醒4类“高考查分陷阱”",
      "url": "https://www.douyin.com/hot/2551748",
      "hot": "10717376"
    },
    {
      "rank": 7,
      "title": "弹壳colt45与无畏契约适配度",
      "url": "https://www.douyin.com/hot/2552121",
      "hot": "9542660"
    },
    {
      "rank": 8,
      "title": "拜见各地美食大王",
      "url": "https://www.douyin.com/hot/2552134",
      "hot": "9468461"
    },
    {
      "rank": 9,
      "title": "恋与深空道歉就够了吗",
      "url": "https://www.douyin.com/hot/2551978",
      "hot": "9396977"
    },
    {
      "rank": 10,
      "title": "净网：杨某诋毁袁隆平院士科研成果被刑拘",
      "url": "https://www.douyin.com/hot/2552414",
      "hot": "9253156"
    }
  ]
}
