{
  "source": "douyin",
  "title": "抖音热点",
  "updated_at": "2026-07-13T04:46:23+00:00",
  "fetch_ok": true,
  "items": [
    {
      "rank": 1,
      "title": "贵州火把节已经准备就绪了",
      "url": "https://www.douyin.com/hot/2568138",
      "hot": "12093088"
    },
    {
      "rank": 2,
      "title": "三伏天记录我的减肥日常",
      "url": "https://www.douyin.com/hot/2569043",
      "hot": "11981318"
    },
    {
      "rank": 3,
      "title": "我国多领域解锁硬核成就",
      "url": "https://www.douyin.com/hot/2569058",
      "hot": "11755439"
    },
    {
      "rank": 4,
      "title": "沈阳暴雨",
      "url": "https://www.douyin.com/hot/2568921",
      "hot": "11458204"
    },
    {
      "rank": 5,
      "title": "用旧凉席打造岳武穆战甲",
      "url": "https://www.douyin.com/hot/2567898",
      "hot": "10308203"
    },
    {
      "rank": 6,
      "title": "火烧云落进千里江山图美到窒息",
      "url": "https://www.douyin.com/hot/2567069",
      "hot": "10268811"
    },
    {
      "rank": 7,
      "title": "酱油洗洁精拉花练习",
      "url": "https://www.douyin.com/hot/2567940",
      "hot": "9133697"
    },
    {
      "rank": 8,
      "title": "昆明版水上闯关太好玩了",
      "url": "https://www.douyin.com/hot/2567919",
      "hot": "9058676"
    },
    {
      "rank": 9,
      "title": "A股",
      "url": "https://www.douyin.com/hot/2569192",
      "hot": "8975741"
    },
    {
      "rank": 10,
      "title": "这夏夯爆了",
      "url": "https://www.douyin.com/hot/2569315",
      "hot": "8637309"
    }
  ]
}
