{
  "source": "hupu",
  "title": "虎扑",
  "updated_at": "2026-07-22T20:53:18+00:00",
  "fetch_ok": true,
  "items": [
    {
      "rank": 1,
      "title": "哈哈哈哈哈哈哈",
      "url": "https://bbs.hupu.com/641185031.html",
      "hot": "0"
    },
    {
      "rank": 2,
      "title": "分享人生的一次艳遇",
      "url": "https://bbs.hupu.com/640995701.html",
      "hot": "593"
    },
    {
      "rank": 3,
      "title": "呵呵",
      "url": "https://bbs.hupu.com/641185022.html",
      "hot": "0"
    },
    {
      "rank": 4,
      "title": "不说换字对不对，关键是不好看啊",
      "url": "https://bbs.hupu.com/641185017.html",
      "hot": "0"
    },
    {
      "rank": 5,
      "title": "绷住挑战！你能不能不要笑了！地狱级！",
      "url": "https://bbs.hupu.com/641184909.html",
      "hot": "2"
    },
    {
      "rank": 6,
      "title": "252：听“淡淡”的播客，做“淡淡”的人！",
      "url": "https://bbs.hupu.com/641184978.html",
      "hot": "1"
    },
    {
      "rank": 7,
      "title": "这玩意国内没人敢吃吧",
      "url": "https://bbs.hupu.com/640754764.html",
      "hot": "65"
    },
    {
      "rank": 8,
      "title": "张路这个职业球员，职业解说员，北京国安俱乐部总经理都在说梅西不行，不知道你们还在杠什么",
      "url": "https://bbs.hupu.com/641160547.html",
      "hot": "70"
    },
    {
      "rank": 9,
      "title": "逾期彻底成黑户煎熬吗？有过来人吗",
      "url": "https://bbs.hupu.com/640919333.html",
      "hot": "15"
    },
    {
      "rank": 10,
      "title": "sunny77",
      "url": "https://bbs.hupu.com/641036869.html",
      "hot": "341"
    }
  ]
}
