{
  "source": "huxiu",
  "title": "虎嗅",
  "updated_at": "2026-07-04T07:32:04+00:00",
  "fetch_ok": true,
  "items": [
    {
      "rank": 1,
      "title": "警方通报“15岁少年在家中和同学饮酒后死亡”：系一氧化碳中毒",
      "url": "https://www.huxiu.com/moment/1260072.html",
      "hot": "0"
    },
    {
      "rank": 2,
      "title": "高市早苗与莫迪兄妹相称，却拒绝喝印度水，“漱口也不行”，专机上装满了瓶装矿泉水",
      "url": "https://www.huxiu.com/moment/1260071.html",
      "hot": "0"
    },
    {
      "rank": 3,
      "title": "美国独立250年国庆日遭高温扰乱：纽约1.7万户居民停电，多座城市考虑取消或调整游行、音乐会和烟花秀；民调显示近半受访者不知国庆日渊源",
      "url": "https://www.huxiu.com/moment/1260070.html",
      "hot": "0"
    },
    {
      "rank": 4,
      "title": "日本东京举办活动庆祝美国建国250周年，无人机组成高市早苗依偎特朗普画面，美网友吐槽：我们用核弹炸他们，他们却对我们这么好",
      "url": "https://www.huxiu.com/moment/1260069.html",
      "hot": "0"
    },
    {
      "rank": 5,
      "title": "两协会倡议规范引导情感陪伴人形机器人健康发展：行业应把安全伦理规范要求融入产品设计、研发、广告宣传、应用全过程，加强个人信息保护",
      "url": "https://www.huxiu.com/moment/1260068.html",
      "hot": "0"
    },
    {
      "rank": 6,
      "title": "男子破坏竞争公司的换电柜被抓现行，警方已立案！嫌犯所属公司：因为这事，品牌都没了",
      "url": "https://www.huxiu.com/moment/1260067.html",
      "hot": "0"
    },
    {
      "rank": 7,
      "title": "广州提醒：局地有龙卷风险",
      "url": "https://www.huxiu.com/moment/1260066.html",
      "hot": "0"
    },
    {
      "rank": 8,
      "title": "高市早苗访问印度签署协议建设1000家沼气工厂，引发网民质疑",
      "url": "https://www.huxiu.com/moment/1260065.html",
      "hot": "0"
    },
    {
      "rank": 9,
      "title": "奕境汽车发布“天穹智盾”安全架构 华为乾崑完成智驾暗夜首测",
      "url": "https://www.huxiu.com/moment/1260021.html",
      "hot": "0"
    },
    {
      "rank": 10,
      "title": "影石回应：继续反诉大疆侵权，大疆美国撤诉转战国内",
      "url": "https://www.huxiu.com/moment/1260062.html",
      "hot": "1"
    }
  ]
}
