{
  "source": "huxiu",
  "title": "虎嗅",
  "updated_at": "2026-07-04T17:18:49+00:00",
  "fetch_ok": true,
  "items": [
    {
      "rank": 1,
      "title": "审视欧盟自动生物识别出入境边境系统的困难推出，机场运营商警告在暑假前可能出现严重延误",
      "url": "https://www.huxiu.com/moment/1260138.html",
      "hot": "0"
    },
    {
      "rank": 2,
      "title": "不止于观影！电影院要成为“潮玩新地标”",
      "url": "https://www.huxiu.com/moment/1260137.html",
      "hot": "0"
    },
    {
      "rank": 3,
      "title": "土耳其总统与巴基斯坦总理举行会谈，讨论多领域合作",
      "url": "https://www.huxiu.com/moment/1260136.html",
      "hot": "0"
    },
    {
      "rank": 4,
      "title": "中国足协最新聘任决定",
      "url": "https://www.huxiu.com/moment/1260135.html",
      "hot": "0"
    },
    {
      "rank": 5,
      "title": "辽宁抚顺特大暴雨致3人死亡",
      "url": "https://www.huxiu.com/moment/1260134.html",
      "hot": "1"
    },
    {
      "rank": 6,
      "title": "四川一轿车行驶中两名儿童坐天窗边，交警回应",
      "url": "https://www.huxiu.com/moment/1260133.html",
      "hot": "0"
    },
    {
      "rank": 7,
      "title": "南瓜暗藏毒品，昆明海关查获超188公斤冰毒",
      "url": "https://www.huxiu.com/moment/1260132.html",
      "hot": "0"
    },
    {
      "rank": 8,
      "title": "字节跳动如何通过其Seedance视频生成器在好莱坞取得进展，得益于低价、惊人的真实感以及时间轴提示等功能",
      "url": "https://www.huxiu.com/moment/1260131.html",
      "hot": "0"
    },
    {
      "rank": 9,
      "title": "航行警告：中国人民解放军某部将在长江下游黄冈公铁大桥附近水域进行军事活动，附近水域临时交通管制",
      "url": "https://www.huxiu.com/moment/1260130.html",
      "hot": "1"
    },
    {
      "rank": 10,
      "title": "沙特媒体：美伊新一轮会谈11日将在巴基斯坦举行",
      "url": "https://www.huxiu.com/moment/1260129.html",
      "hot": "0"
    }
  ]
}
