{
  "source": "jianshu",
  "title": "简书今日热点",
  "updated_at": "2026-07-17T08:18:50+00:00",
  "fetch_ok": true,
  "items": [
    {
      "rank": 1,
      "title": "诸葛亮38 刘备晚年的权力困局",
      "url": "https://www.jianshu.com/p/2df1665f1ce1",
      "hot": "4005"
    },
    {
      "rank": 2,
      "title": "摩天轮的摩天是啥？",
      "url": "https://www.jianshu.com/p/ee971744f89c",
      "hot": "0"
    },
    {
      "rank": 3,
      "title": "在希望的田野上",
      "url": "https://www.jianshu.com/p/39a143faff73",
      "hot": "2932"
    },
    {
      "rank": 4,
      "title": "读《世说新语》（0386）：二王神宇",
      "url": "https://www.jianshu.com/p/ea71a641c64c",
      "hot": "10805"
    },
    {
      "rank": 5,
      "title": "心梦丨我梦到了自己的工作焦虑",
      "url": "https://www.jianshu.com/p/e1196a965815",
      "hot": "4047"
    },
    {
      "rank": 6,
      "title": "从“想创业”到“真卖货”，我只花了一个周末：格行视精灵的零成本试错全记录",
      "url": "https://www.jianshu.com/p/74d9c5aa7b05",
      "hot": "0"
    },
    {
      "rank": 7,
      "title": "东山相遇|躬耕东山沃土 巾帼绽放芳华",
      "url": "https://www.jianshu.com/p/6244b34523a8",
      "hot": "0"
    }
  ]
}
