{
  "source": "jianshu",
  "title": "简书今日热点",
  "updated_at": "2026-06-14T10:29:47+00:00",
  "fetch_ok": true,
  "items": [
    {
      "rank": 1,
      "title": "预热： 四维（及以上）概念",
      "url": "https://www.jianshu.com/p/910b059c86cc",
      "hot": "5150"
    },
    {
      "rank": 2,
      "title": "第三十一章 番外·真相揭秘",
      "url": "https://www.jianshu.com/p/1c339b655da3",
      "hot": "787"
    },
    {
      "rank": 3,
      "title": "💐说说“飞书”和“IMA”",
      "url": "https://www.jianshu.com/p/90f1cfee62c8",
      "hot": "812"
    },
    {
      "rank": 4,
      "title": "歌词本|One I love",
      "url": "https://www.jianshu.com/p/5920e5794067",
      "hot": "6860"
    },
    {
      "rank": 5,
      "title": "跟着Nature学作图:R语言ggplot2环形堆积柱形图完整示例",
      "url": "https://www.jianshu.com/p/aeed556d34f2",
      "hot": "12049"
    },
    {
      "rank": 6,
      "title": "市政燃气管网智能化改造，离不开智能测试桩",
      "url": "https://www.jianshu.com/p/7acd89e0fa80",
      "hot": "0"
    },
    {
      "rank": 7,
      "title": "时间慢谈27：油腻宰相如何把老板、同事全都哄上青云（《史记》公孙弘）",
      "url": "https://www.jianshu.com/p/7a81cf1b23dd",
      "hot": "0"
    },
    {
      "rank": 8,
      "title": "gitlab webhook 回调方法使用",
      "url": "https://www.jianshu.com/p/1d6a9dae0b51",
      "hot": "1532"
    },
    {
      "rank": 9,
      "title": "如何写金句",
      "url": "https://www.jianshu.com/p/0fb887ce95db",
      "hot": "11154"
    },
    {
      "rank": 10,
      "title": "使用nvm在Windows上管理Node版本",
      "url": "https://www.jianshu.com/p/5f7cbefda406",
      "hot": "19220"
    }
  ]
}
