{
  "source": "kuaishou",
  "title": "快手热榜",
  "updated_at": "2026-07-21T21:01:01+00:00",
  "fetch_ok": true,
  "items": [
    {
      "rank": 1,
      "title": "总书记的一周",
      "url": "https://www.kuaishou.com/short-video/3xiejgwyxivu8r2",
      "hot": ""
    },
    {
      "rank": 2,
      "title": "菲律宾先动手还倒打一耙",
      "url": "https://www.kuaishou.com/short-video/3xtvanmg74vzp9g",
      "hot": "1318.5万"
    },
    {
      "rank": 3,
      "title": "女子闪婚出轨婚介被立案",
      "url": "https://www.kuaishou.com/short-video/3xhc2wewug2r8i6",
      "hot": "1242.6万"
    },
    {
      "rank": 4,
      "title": "科技向善 共享未来",
      "url": "https://www.kuaishou.com/short-video/3x926wn8bcetxps",
      "hot": "1194.4万"
    },
    {
      "rank": 5,
      "title": "云南普洱发生5.0级地震",
      "url": "https://www.kuaishou.com/short-video/3xe96d7u2eh99nu",
      "hot": "1146.1万"
    },
    {
      "rank": 6,
      "title": "墨江受灾群众已妥善安置",
      "url": "https://www.kuaishou.com/short-video/3x8826fpymcez4s",
      "hot": "1123.6万"
    },
    {
      "rank": 7,
      "title": "老人全网寻20年前恩人",
      "url": "https://www.kuaishou.com/short-video/3x2d9bvjzvifiuk",
      "hot": "1101.5万"
    },
    {
      "rank": 8,
      "title": "张柏芝月中火速安排大儿子回香港",
      "url": "https://www.kuaishou.com/short-video/3xfpbdpn9ph3gus",
      "hot": "1079.6万"
    },
    {
      "rank": 9,
      "title": "沈阳车主上演防淹天花板",
      "url": "https://www.kuaishou.com/short-video/3xfj2yacjimnbw9",
      "hot": "1057.7万"
    },
    {
      "rank": 10,
      "title": "美国公布美军基地遭袭画面",
      "url": "https://www.kuaishou.com/short-video/3xsiup8e952k2pm",
      "hot": "1035.3万"
    }
  ]
}
