{
  "source": "kuaishou",
  "title": "快手热榜",
  "updated_at": "2026-06-23T20:26:08+00:00",
  "fetch_ok": true,
  "items": [
    {
      "rank": 1,
      "title": "C罗打入本届世界杯首球",
      "url": "https://www.kuaishou.com/short-video/3xywnmqbyvnjn5w",
      "hot": "1233万"
    },
    {
      "rank": 2,
      "title": "葡萄牙5比0大胜乌兹别克斯坦",
      "url": "https://www.kuaishou.com/short-video/3xiz36n3siefhi6",
      "hot": "1232.5万"
    },
    {
      "rank": 3,
      "title": "2026年十大新兴技术出炉",
      "url": "https://www.kuaishou.com/short-video/3xwskgu64e44yqm",
      "hot": "1232.2万"
    },
    {
      "rank": 4,
      "title": "双胞胎高考双双过650分",
      "url": "https://www.kuaishou.com/short-video/3x28zg4accvkqu2",
      "hot": "1232万"
    },
    {
      "rank": 5,
      "title": "微信迎史上最大更新",
      "url": "https://www.kuaishou.com/short-video/3x9yjmu4vczudve",
      "hot": "1160.2万"
    },
    {
      "rank": 6,
      "title": "男生高考649分妈妈狂亲",
      "url": "https://www.kuaishou.com/short-video/3xj7deiuvx3shha",
      "hot": "1116.6万"
    },
    {
      "rank": 7,
      "title": "东北老爸投喂30多岁女儿",
      "url": "https://www.kuaishou.com/short-video/3xhvaidayt3nzi9",
      "hot": "1095.3万"
    },
    {
      "rank": 8,
      "title": "英格兰vs加纳",
      "url": "https://www.kuaishou.com/short-video/3xztum3qxicnvhs",
      "hot": "1084.8万"
    },
    {
      "rank": 9,
      "title": "韩国总理到访母校清华大学",
      "url": "https://www.kuaishou.com/short-video/3xf88mvghs2fweu",
      "hot": "1074.3万"
    },
    {
      "rank": 10,
      "title": "刘建宏向C罗致敬",
      "url": "https://www.kuaishou.com/short-video/3xrwybzb2ey6wvi",
      "hot": "1051.8万"
    }
  ]
}
