{
  "source": "netease",
  "title": "网易新闻",
  "updated_at": "2026-07-08T09:15:37+00:00",
  "fetch_ok": true,
  "items": [
    {
      "rank": 1,
      "title": "美军再对伊朗发动打击，当面一套背面一套的特朗普，已毫无信用可言",
      "url": "https://www.163.com/dy/article/L1B3EF2505561FVR.html",
      "hot": ""
    },
    {
      "rank": 2,
      "title": "拒绝勇士7500万，拒湖人2000万，都说你飘了，小托马斯是前车之鉴",
      "url": "https://www.163.com/dy/article/L1B39DJC0529AVSD.html",
      "hot": ""
    },
    {
      "rank": 3,
      "title": "杰弗森：詹姆斯已告诉我要去哪，他让我保密",
      "url": "https://www.163.com/dy/article/L1B379OQ05299JMD.html",
      "hot": ""
    },
    {
      "rank": 4,
      "title": "马卡报：迈阿密国际有意免签沃齐尼亚，巴乙多家俱乐部竞争",
      "url": "https://www.163.com/dy/article/L1B30ENU0549BAP0.html",
      "hot": ""
    },
    {
      "rank": 5,
      "title": "华为哈勃退出中科晶禾",
      "url": "https://www.163.com/dy/article/L1B2NIIS0539ARRF.html",
      "hot": ""
    },
    {
      "rank": 6,
      "title": "骑士签约詹姆斯方案出炉：哈登降薪续约，送走斯特鲁斯+施罗德！",
      "url": "https://www.163.com/dy/article/L1B2AU5R05560PER.html",
      "hot": ""
    },
    {
      "rank": 7,
      "title": "葡萄牙足协主席：葡萄牙表现远低预期；新帅有望在本周内确定",
      "url": "https://www.163.com/dy/article/L1B2BV4N0549BAP0.html",
      "hot": ""
    },
    {
      "rank": 8,
      "title": "特朗普：美伊谅解备忘录“已终结”",
      "url": "https://www.163.com/dy/article/L1B1N8UT0534A4SC.html",
      "hot": ""
    },
    {
      "rank": 9,
      "title": "特朗普要求全面切断与西班牙贸易",
      "url": "https://www.163.com/dy/article/L1B146IR0550WHYR.html",
      "hot": ""
    },
    {
      "rank": 10,
      "title": "横州六蓝村村民讲述：“水不是慢慢涨，是直接‘喷’下来的”；记录广西洪水中的救援转移片段",
      "url": "https://www.163.com/dy/article/L1B08K9T05129QAF.html",
      "hot": ""
    }
  ]
}
