{
  "source": "ngabbs",
  "title": "NGA",
  "updated_at": "2026-07-22T21:55:19+00:00",
  "fetch_ok": true,
  "items": [
    {
      "rank": 1,
      "title": "iOS升级18.4后请下载新版APP",
      "url": "https://bbs.nga.cn/read.php?tid=44040507",
      "hot": "0"
    },
    {
      "rank": 2,
      "title": "iOS升级18.4后请下载新版APP",
      "url": "https://bbs.nga.cn/read.php?tid=44040507",
      "hot": "0"
    },
    {
      "rank": 3,
      "title": "iOS升级18.4后请下载新版APP",
      "url": "https://bbs.nga.cn/read.php?tid=44040507",
      "hot": "0"
    },
    {
      "rank": 4,
      "title": "iOS升级18.4后请下载新版APP",
      "url": "https://bbs.nga.cn/read.php?tid=44040507",
      "hot": "0"
    },
    {
      "rank": 5,
      "title": "iOS升级18.4后请下载新版APP",
      "url": "https://bbs.nga.cn/read.php?tid=44040507",
      "hot": "0"
    },
    {
      "rank": 6,
      "title": "小伙子格局不错",
      "url": "https://bbs.nga.cn/read.php?tid=47237485",
      "hot": "110"
    },
    {
      "rank": 7,
      "title": "中立观众，新开一个户外团播的帖子吧(绝不隐藏和删帖，欢迎讨论)",
      "url": "https://bbs.nga.cn/read.php?tid=46985663",
      "hot": "40549"
    },
    {
      "rank": 8,
      "title": "这样的土壤，不配获得国家队进入世界杯的欢愉",
      "url": "https://bbs.nga.cn/read.php?tid=47237793",
      "hot": "62"
    },
    {
      "rank": 9,
      "title": "国服特色插件，除了biaoge，下一个会不会是NCL ？",
      "url": "https://bbs.nga.cn/read.php?tid=47237463",
      "hot": "59"
    },
    {
      "rank": 10,
      "title": "一直没忍心看决赛，听说阿根廷被踢的还不了手？",
      "url": "https://bbs.nga.cn/read.php?tid=47237594",
      "hot": "47"
    }
  ]
}
