{
  "source": "ngabbs",
  "title": "NGA",
  "updated_at": "2026-07-18T17:32:14+00:00",
  "fetch_ok": true,
  "items": [
    {
      "rank": 1,
      "title": "iOS升级18.4后请下载新版APP",
      "url": "https://bbs.nga.cn/read.php?tid=44040507",
      "hot": "0"
    },
    {
      "rank": 2,
      "title": "iOS升级18.4后请下载新版APP",
      "url": "https://bbs.nga.cn/read.php?tid=44040507",
      "hot": "0"
    },
    {
      "rank": 3,
      "title": "iOS升级18.4后请下载新版APP",
      "url": "https://bbs.nga.cn/read.php?tid=44040507",
      "hot": "0"
    },
    {
      "rank": 4,
      "title": "iOS升级18.4后请下载新版APP",
      "url": "https://bbs.nga.cn/read.php?tid=44040507",
      "hot": "0"
    },
    {
      "rank": 5,
      "title": "iOS升级18.4后请下载新版APP",
      "url": "https://bbs.nga.cn/read.php?tid=44040507",
      "hot": "0"
    },
    {
      "rank": 6,
      "title": "中立观众，新开一个户外团播的帖子吧(绝不隐藏和删帖，欢迎讨论)",
      "url": "https://bbs.nga.cn/read.php?tid=46985663",
      "hot": "34913"
    },
    {
      "rank": 7,
      "title": "[外赛区赛事] 2026LCK联赛讨论帖",
      "url": "https://bbs.nga.cn/read.php?tid=46417092",
      "hot": "58804"
    },
    {
      "rank": 8,
      "title": "我是世界上最幸福的kg",
      "url": "https://bbs.nga.cn/read.php?tid=47211640",
      "hot": "59"
    },
    {
      "rank": 9,
      "title": "[国际赛事] 我一直以为dk是lck的下水道，杂鱼队伍",
      "url": "https://bbs.nga.cn/read.php?tid=47205159",
      "hot": "43"
    },
    {
      "rank": 10,
      "title": "7月1日起，湖北省女员工可申请居家办公",
      "url": "https://bbs.nga.cn/read.php?tid=47208724",
      "hot": "37"
    }
  ]
}
