{
  "source": "nodeseek",
  "title": "NodeSeek",
  "updated_at": "2026-07-13T10:48:42+00:00",
  "fetch_ok": true,
  "items": [
    {
      "rank": 1,
      "title": "【剩余价值出】家人Nosla站洛杉矶149/y",
      "url": "https://www.nodeseek.com/post-820090-1",
      "hot": ""
    },
    {
      "rank": 2,
      "title": "图床怎么用救我，联通大概能薅10块钱，",
      "url": "https://www.nodeseek.com/post-820088-1",
      "hot": ""
    },
    {
      "rank": 3,
      "title": "codex 最近老是重连？",
      "url": "https://www.nodeseek.com/post-820087-1",
      "hot": ""
    },
    {
      "rank": 4,
      "title": "49出dartnode 7刀休斯顿",
      "url": "https://www.nodeseek.com/post-820086-1",
      "hot": ""
    },
    {
      "rank": 5,
      "title": "家人云有点牛逼啊",
      "url": "https://www.nodeseek.com/post-820085-1",
      "hot": ""
    },
    {
      "rank": 6,
      "title": "gpt 20x pro 还有四次重置，如何能快速蹬完，没打过这么富裕的仗",
      "url": "https://www.nodeseek.com/post-820084-1",
      "hot": ""
    },
    {
      "rank": 7,
      "title": "[开源] NarraNexus：让多个有长期记忆的 Agent 真正协作起来",
      "url": "https://www.nodeseek.com/post-820083-1",
      "hot": ""
    },
    {
      "rank": 8,
      "title": "[测试留档]新收的Cloudnium LA",
      "url": "https://www.nodeseek.com/post-820082-1",
      "hot": ""
    },
    {
      "rank": 9,
      "title": "尝试收个po1，可以聊聊，看什么方式合适",
      "url": "https://www.nodeseek.com/post-820081-1",
      "hot": ""
    },
    {
      "rank": 10,
      "title": "【NQ留档】Scaleway(online) 3.44o Netherlands/AMS1 4GB 1TB 1Gbit Unmetered BW",
      "url": "https://www.nodeseek.com/post-820080-1",
      "hot": ""
    }
  ]
}
