{
  "source": "oschina",
  "title": "开源中国",
  "updated_at": "2026-07-13T04:47:12+00:00",
  "fetch_ok": true,
  "items": [
    {
      "rank": 1,
      "title": "DataBuff v0.1.3：SkyWalking 一行接入 + 运维专家 SSH 排障上线",
      "url": "https://www.oschina.net/news/471671/databuff-0-1-3-released",
      "hot": "Mon, 13 Jul 2026 10:55:52 +0800"
    },
    {
      "rank": 2,
      "title": "零代码接口测试 APIAuto 6，AI Agent 自动操作&amp;读写 DB :fire: Star 2K+",
      "url": "https://www.oschina.net/news/471668",
      "hot": "Mon, 13 Jul 2026 10:19:48 +0800"
    },
    {
      "rank": 3,
      "title": "预签名上传链接、传输速度与剩余时间、迁移可从面板重试，以及七家云通用的对象标签读写",
      "url": "https://www.oschina.net/news/471666",
      "hot": "Mon, 13 Jul 2026 10:12:32 +0800"
    },
    {
      "rank": 4,
      "title": "用 Solon AI ReActAgent 落地智能客服工单处理",
      "url": "https://www.oschina.net/news/471665",
      "hot": "Mon, 13 Jul 2026 09:55:00 +0800"
    },
    {
      "rank": 5,
      "title": "Guns 8.4.0 正式发布，企业版已开源",
      "url": "https://www.oschina.net/news/471664",
      "hot": "Mon, 13 Jul 2026 09:51:55 +0800"
    },
    {
      "rank": 6,
      "title": "🚀 Rust 首个零代码接口和文档开源，腾讯 APIJSON 生态项目",
      "url": "https://www.oschina.net/news/471663",
      "hot": "Mon, 13 Jul 2026 09:49:49 +0800"
    },
    {
      "rank": 7,
      "title": "ShowDoc AI 智能体上线",
      "url": "https://www.oschina.net/news/471662",
      "hot": "Mon, 13 Jul 2026 09:47:44 +0800"
    },
    {
      "rank": 8,
      "title": "正式开源！美团 LongCat-2.0 同步开放国产卡推理代码",
      "url": "https://my.oschina.net/meituantech/blog/19721031",
      "hot": "Mon, 13 Jul 2026 09:30:47 +0800"
    },
    {
      "rank": 9,
      "title": "DDNS 动态域名工具更新，新增管理员登录，前端优化",
      "url": "https://www.oschina.net/news/471660",
      "hot": "Mon, 13 Jul 2026 08:10:39 +0800"
    },
    {
      "rank": 10,
      "title": "MateClaw 1.8.0 发布: 打通写材料场景，可以直接写公众号和小红书",
      "url": "https://www.oschina.net/news/471659",
      "hot": "Sun, 12 Jul 2026 21:08:28 +0800"
    }
  ]
}
