{
  "source": "qqnews",
  "title": "腾讯新闻",
  "updated_at": "2026-07-05T20:03:02+00:00",
  "fetch_ok": true,
  "items": [
    {
      "rank": 1,
      "title": "齐心协力走好新的长征路",
      "url": "https://new.qq.com/rain/a/20260705A03V9L00",
      "hot": "700125"
    },
    {
      "rank": 2,
      "title": "暴雨、台风、强对流天气 中央气象台六预警齐发",
      "url": "https://new.qq.com/rain/a/20260705A077CM00",
      "hot": "1882908"
    },
    {
      "rank": 3,
      "title": "财经调查丨偷金手段曝光！总台起底专供黄金回收的作弊秤",
      "url": "https://new.qq.com/rain/a/20260705A088DV00",
      "hot": "1675739"
    },
    {
      "rank": 4,
      "title": "视频丨航线上新、票价亲民、签转便捷 暑期乘机出行迎多重便利",
      "url": "https://new.qq.com/rain/a/20260705A04NJO00",
      "hot": "1565902"
    },
    {
      "rank": 5,
      "title": "“东风快递”，送达画面曝光",
      "url": "https://new.qq.com/rain/a/20260705V05VE300",
      "hot": "1508203"
    },
    {
      "rank": 6,
      "title": "官方回应“重庆网红打出租车到拉萨视频爆火”：将及时兑现奖励资金",
      "url": "https://new.qq.com/rain/a/20260705A04QY800",
      "hot": "1473922"
    },
    {
      "rank": 7,
      "title": "政府采购违法违规，要“开刀”了",
      "url": "https://new.qq.com/rain/a/20260705A06XHD00",
      "hot": "1455611"
    },
    {
      "rank": 8,
      "title": "过分！巴拉圭门将拿球砸姆巴佩 竟当选MVP 网友：应该让马宁执法",
      "url": "https://new.qq.com/rain/a/20260705A02MAJ00",
      "hot": "1442556"
    },
    {
      "rank": 9,
      "title": "为什么欧洲人热死都不装空调？",
      "url": "https://new.qq.com/rain/a/20260705A05QI900",
      "hot": "1433264"
    },
    {
      "rank": 10,
      "title": "世界杯神奇门将带火佛得角！搜索热度大涨200%，落地签停留期30天",
      "url": "https://new.qq.com/rain/a/20260705A05VPX00",
      "hot": "1427602"
    }
  ]
}
