{
  "source": "readhub",
  "title": "Readhub",
  "updated_at": "2026-07-20T23:12:10+00:00",
  "fetch_ok": true,
  "items": [
    {
      "rank": 1,
      "title": "部分地区有大暴雨 交通运输部启动强降雨三级防御响应",
      "url": "https://readhub.cn/topic/8uv6a7ajJ5D",
      "hot": "Mon, 20 Jul 2026 23:05:24 GMT"
    },
    {
      "rank": 2,
      "title": "三星生物拟 122 亿元收购瑞士多肽企业 PolyPeptide",
      "url": "https://readhub.cn/topic/8uvFXGF54QZ",
      "hot": "Mon, 20 Jul 2026 22:10:31 GMT"
    },
    {
      "rank": 3,
      "title": "小米首款耳夹式耳机新功能上线：双向通话翻译、英语口语陪练",
      "url": "https://readhub.cn/topic/8uupml8zAIz",
      "hot": "Mon, 20 Jul 2026 22:10:31 GMT"
    },
    {
      "rank": 4,
      "title": "四川多地升级高温红色预警 最高气温突破 42℃",
      "url": "https://readhub.cn/topic/8uuiHDu6pVm",
      "hot": "Mon, 20 Jul 2026 22:05:20 GMT"
    },
    {
      "rank": 5,
      "title": "霍尔木兹海峡商船通行量降至战前一成 美军双航母持续实施海上封锁",
      "url": "https://readhub.cn/topic/8uuQ5TiHGy9",
      "hot": "Mon, 20 Jul 2026 20:40:38 GMT"
    },
    {
      "rank": 6,
      "title": "AMC 院线大涨超 25%，Q2 财报全面超预期",
      "url": "https://readhub.cn/topic/8uvP98xCXQh",
      "hot": "Mon, 20 Jul 2026 20:15:29 GMT"
    },
    {
      "rank": 7,
      "title": "热门中概股普涨 阿里巴巴 (BABA.US) 涨逾 3%",
      "url": "https://readhub.cn/topic/8uvBEeZhYSo",
      "hot": "Mon, 20 Jul 2026 20:15:29 GMT"
    },
    {
      "rank": 8,
      "title": "三星电子晶圆代工正评估将美国泰勒厂的初期生产规模扩大至原计划的 2 倍",
      "url": "https://readhub.cn/topic/8uugqbbV9Pl",
      "hot": "Mon, 20 Jul 2026 18:40:35 GMT"
    },
    {
      "rank": 9,
      "title": "中国使馆证实 3 名中国公民在俄境内无人机袭击中受伤",
      "url": "https://readhub.cn/topic/8uvMIOyORBs",
      "hot": "Mon, 20 Jul 2026 17:40:32 GMT"
    },
    {
      "rank": 10,
      "title": "长和回应有关屈臣氏 IPO 的报道：尚未作出任何决定",
      "url": "https://readhub.cn/topic/8uuthvMTXRJ",
      "hot": "Mon, 20 Jul 2026 17:32:16 GMT"
    }
  ]
}
