{
  "source": "readhub",
  "title": "Readhub",
  "updated_at": "2026-06-28T14:10:32+00:00",
  "fetch_ok": true,
  "items": [
    {
      "rank": 1,
      "title": "俄称乌军 24 小时内多次袭击扎波罗热核电站",
      "url": "https://readhub.cn/topic/8uKjKujNck4",
      "hot": "Sun, 28 Jun 2026 14:06:26 GMT"
    },
    {
      "rank": 2,
      "title": "中国首个高海拔光氢储一体化项目累计发电量超 40 亿千瓦时",
      "url": "https://readhub.cn/topic/8uKfPYWTnzF",
      "hot": "Sun, 28 Jun 2026 13:41:33 GMT"
    },
    {
      "rank": 3,
      "title": "东风奕派 M8 正式开启预售 19.98 万起标配华为乾崑六件套",
      "url": "https://readhub.cn/topic/8uKM5bkOVvc",
      "hot": "Sun, 28 Jun 2026 13:11:38 GMT"
    },
    {
      "rank": 4,
      "title": "水利部安排部署南方地区暴雨洪水防御工作",
      "url": "https://readhub.cn/topic/8uKWTH92WUn",
      "hot": "Sun, 28 Jun 2026 12:46:24 GMT"
    },
    {
      "rank": 5,
      "title": "网传大疆全系涨价 3%-8% ，官方回应：消息不实，无调价计划",
      "url": "https://readhub.cn/topic/8uKahL1qehz",
      "hot": "Sun, 28 Jun 2026 12:40:58 GMT"
    },
    {
      "rank": 6,
      "title": "金山办公：拟以 2.5 亿元-5 亿元回购公司股份",
      "url": "https://readhub.cn/topic/8uKJb8Fzvge",
      "hot": "Sun, 28 Jun 2026 11:11:46 GMT"
    },
    {
      "rank": 7,
      "title": "纳指科技 ETF 景顺 (159509) 6 月 29 日开市起至 10:30 停牌",
      "url": "https://readhub.cn/topic/8uKTYIa8i42",
      "hot": "Sun, 28 Jun 2026 10:45:36 GMT"
    },
    {
      "rank": 8,
      "title": "200 万粉丝网红诋毁袁隆平成果，抖音：相关账号已无限期封禁",
      "url": "https://readhub.cn/topic/8uKM5YUZiRi",
      "hot": "Sun, 28 Jun 2026 10:40:40 GMT"
    },
    {
      "rank": 9,
      "title": "金山办公：拟以 2.5 亿元-5 亿元回购公司股份",
      "url": "https://readhub.cn/topic/8uKIAnvnQH6",
      "hot": "Sun, 28 Jun 2026 09:41:37 GMT"
    },
    {
      "rank": 10,
      "title": "何立峰在四川调研时指出 加快建设现代化产业体系持续增强经济发展动能",
      "url": "https://readhub.cn/topic/8uKIB1HnKhQ",
      "hot": "Sun, 28 Jun 2026 09:11:43 GMT"
    }
  ]
}
