{
  "source": "v2ex",
  "title": "V2EX",
  "updated_at": "2026-06-28T04:55:35+00:00",
  "fetch_ok": true,
  "items": [
    {
      "rank": 1,
      "title": "31 岁，在离婚前夜，我终于承认自己从未真正活过",
      "url": "https://www.v2ex.com/t/1223325",
      "hot": "94"
    },
    {
      "rank": 2,
      "title": "6 年前的洗面奶用完了，现在男的都用啥",
      "url": "https://www.v2ex.com/t/1223399",
      "hot": "49"
    },
    {
      "rank": 3,
      "title": "第一次去丈母娘家，带什么去啊",
      "url": "https://www.v2ex.com/t/1223304",
      "hot": "30"
    },
    {
      "rank": 4,
      "title": "高考 300 多分，想留上海读公办大专，求懂行的前辈指点志愿！",
      "url": "https://www.v2ex.com/t/1223293",
      "hot": "27"
    },
    {
      "rank": 5,
      "title": "同事现在学舞蹈 准备用 AI 换脸和换声音在视频社交平台直播～ 这方案可行么？",
      "url": "https://www.v2ex.com/t/1223346",
      "hot": "24"
    },
    {
      "rank": 6,
      "title": "终端工作区：从 WindTerm 到 NyaTerm",
      "url": "https://www.v2ex.com/t/1223359",
      "hot": "23"
    },
    {
      "rank": 7,
      "title": "在家远程办公太容易分神了",
      "url": "https://www.v2ex.com/t/1223386",
      "hot": "23"
    },
    {
      "rank": 8,
      "title": "尼日利亚礼品卡被干掉后老哥们都是怎么订阅的？",
      "url": "https://www.v2ex.com/t/1223320",
      "hot": "21"
    }
  ]
}
