{
  "source": "wallstreetcn",
  "title": "华尔街见闻",
  "updated_at": "2026-07-01T10:27:24+00:00",
  "fetch_ok": true,
  "items": [
    {
      "rank": 1,
      "title": "美伊在多哈举行间接会谈，聚焦落实谅解备忘录",
      "url": "https://wallstreetcn.com/articles/3775962",
      "hot": ""
    },
    {
      "rank": 2,
      "title": "下周一，A股将告别5%涨跌停板",
      "url": "https://wallstreetcn.com/articles/3775967",
      "hot": ""
    },
    {
      "rank": 3,
      "title": "用“阉割”换“解禁”？Fable5明日回归，但已不是原来的Fable 5",
      "url": "https://wallstreetcn.com/articles/3775963",
      "hot": ""
    },
    {
      "rank": 4,
      "title": "广期所：调整铂、钯期货合约涨跌停板幅度和交易保证金标准",
      "url": "https://wallstreetcn.com/livenews/3127344",
      "hot": ""
    },
    {
      "rank": 5,
      "title": "财政部有关负责同志就新一期世界银行-中国国别伙伴框架涉华贷款有关问题答记者问",
      "url": "https://wallstreetcn.com/livenews/3127342",
      "hot": ""
    },
    {
      "rank": 6,
      "title": "韩国股市又被“小作文”打崩：国民年金被曝7月启动再平衡，或抛售高达74万亿国内股票",
      "url": "https://wallstreetcn.com/articles/3775964",
      "hot": ""
    },
    {
      "rank": 7,
      "title": "立昂微：8英寸重掺杂外延片订单旺盛，12英寸28nm逻辑芯片用硅片已批量供货",
      "url": "https://wallstreetcn.com/livenews/3127324",
      "hot": ""
    },
    {
      "rank": 8,
      "title": "韩国投资者，大买中国资产",
      "url": "https://wallstreetcn.com/articles/3775960",
      "hot": ""
    },
    {
      "rank": 9,
      "title": "美团开源万亿参数大模型 LongCat-2.0，五万卡国产算力全流程训练",
      "url": "https://wallstreetcn.com/articles/3775961",
      "hot": ""
    },
    {
      "rank": 10,
      "title": "市场等待沃什讲话与非农数据，美股盘前存储芯片股走低，康宁跌超4%，黄金再跌1%",
      "url": "https://wallstreetcn.com/articles/3775932",
      "hot": ""
    }
  ]
}
