{
  "source": "weatheralarm",
  "title": "天气预警",
  "updated_at": "2026-07-13T13:07:55+00:00",
  "fetch_ok": true,
  "items": [
    {
      "rank": 1,
      "title": "辽宁省沈阳市浑南区气象台发布暴雨红色预警信号",
      "url": "http://nmc.cn/publish/alarm/21011241600000_20260713205400.html",
      "hot": "2026/07/13 20:54 辽宁省沈阳市浑南区气象台发布暴雨红色预警信号"
    },
    {
      "rank": 2,
      "title": "宁夏回族自治区银川市气象台发布暴雨蓝色预警信号",
      "url": "http://nmc.cn/publish/alarm/64010041600000_20260713205204.html",
      "hot": "2026/07/13 20:52 宁夏回族自治区银川市气象台发布暴雨蓝色预警信号"
    },
    {
      "rank": 3,
      "title": "河北省承德市宽城满族自治县气象台发布暴雨黄色预警信号",
      "url": "http://nmc.cn/publish/alarm/13082741600000_20260713205200.html",
      "hot": "2026/07/13 20:52 河北省承德市宽城满族自治县气象台发布暴雨黄色预警信号"
    },
    {
      "rank": 4,
      "title": "福建省漳州市诏安县气象台发布雷电黄色预警信号",
      "url": "http://nmc.cn/publish/alarm/35062441600000_20260713205200.html",
      "hot": "2026/07/13 20:52 福建省漳州市诏安县气象台发布雷电黄色预警信号"
    },
    {
      "rank": 5,
      "title": "吉林省延边朝鲜族自治州图们市气象台发布地质灾害黄色预警信号",
      "url": "http://nmc.cn/publish/alarm/22240241600000_20260713205119.html",
      "hot": "2026/07/13 20:51 吉林省延边朝鲜族自治州图们市气象台发布地质灾害黄色预警信号"
    },
    {
      "rank": 6,
      "title": "辽宁省沈阳市法库县气象台发布雷雨大风黄色预警信号",
      "url": "http://nmc.cn/publish/alarm/21012441600000_20260713204900.html",
      "hot": "2026/07/13 20:49 辽宁省沈阳市法库县气象台发布雷雨大风黄色预警信号"
    },
    {
      "rank": 7,
      "title": "新疆维吾尔自治区博尔塔拉蒙古自治州精河县气象台发布雷电黄色预警信号",
      "url": "http://nmc.cn/publish/alarm/65272241600000_20260713204756.html",
      "hot": "2026/07/13 20:47 新疆维吾尔自治区博尔塔拉蒙古自治州精河县气象台发布雷电黄色预警信号"
    },
    {
      "rank": 8,
      "title": "江苏省连云港市东海县气象台发布暴雨蓝色预警信号",
      "url": "http://nmc.cn/publish/alarm/32072241600000_20260713204738.html",
      "hot": "2026/07/13 20:47 江苏省连云港市东海县气象台发布暴雨蓝色预警信号"
    },
    {
      "rank": 9,
      "title": "吉林省通化市通化县气象台发布地质灾害橙色预警信号",
      "url": "http://nmc.cn/publish/alarm/22052141600000_20260713204650.html",
      "hot": "2026/07/13 20:46 吉林省通化市通化县气象台发布地质灾害橙色预警信号"
    },
    {
      "rank": 10,
      "title": "广西壮族自治区来宾市武宣县气象台发布雷电黄色预警信号",
      "url": "http://nmc.cn/publish/alarm/45132341600000_20260713204622.html",
      "hot": "2026/07/13 20:46 广西壮族自治区来宾市武宣县气象台发布雷电黄色预警信号"
    }
  ]
}
