{
  "source": "weibo",
  "title": "微博热搜",
  "updated_at": "2026-06-21T09:05:15+00:00",
  "fetch_ok": true,
  "items": [
    {
      "rank": 1,
      "title": "蔡磊说将亲眼见证渐冻症被终结",
      "url": "https://s.weibo.com/weibo?q=%E8%94%A1%E7%A3%8A%E8%AF%B4%E5%B0%86%E4%BA%B2%E7%9C%BC%E8%A7%81%E8%AF%81%E6%B8%90%E5%86%BB%E7%97%87%E8%A2%AB%E7%BB%88%E7%BB%93",
      "hot": ""
    },
    {
      "rank": 2,
      "title": "人民日报批烂梗泛滥",
      "url": "https://s.weibo.com/weibo?q=%E4%BA%BA%E6%B0%91%E6%97%A5%E6%8A%A5%E6%89%B9%E7%83%82%E6%A2%97%E6%B3%9B%E6%BB%A5",
      "hot": ""
    },
    {
      "rank": 3,
      "title": "端午文旅消费新体验",
      "url": "https://s.weibo.com/weibo?q=%E7%AB%AF%E5%8D%88%E6%96%87%E6%97%85%E6%B6%88%E8%B4%B9%E6%96%B0%E4%BD%93%E9%AA%8C",
      "hot": ""
    },
    {
      "rank": 4,
      "title": "徐梦洁道歉",
      "url": "https://s.weibo.com/weibo?q=%E5%BE%90%E6%A2%A6%E6%B4%81%E9%81%93%E6%AD%89",
      "hot": ""
    },
    {
      "rank": 5,
      "title": "长期熬夜相当于给人生调休了",
      "url": "https://s.weibo.com/weibo?q=%E9%95%BF%E6%9C%9F%E7%86%AC%E5%A4%9C%E7%9B%B8%E5%BD%93%E4%BA%8E%E7%BB%99%E4%BA%BA%E7%94%9F%E8%B0%83%E4%BC%91%E4%BA%86",
      "hot": ""
    },
    {
      "rank": 6,
      "title": "我不知道螺蛳粉你这是怎么了",
      "url": "https://s.weibo.com/weibo?q=%E6%88%91%E4%B8%8D%E7%9F%A5%E9%81%93%E8%9E%BA%E8%9B%B3%E7%B2%89%E4%BD%A0%E8%BF%99%E6%98%AF%E6%80%8E%E4%B9%88%E4%BA%86",
      "hot": ""
    },
    {
      "rank": 7,
      "title": "高考志愿指南",
      "url": "https://s.weibo.com/weibo?q=%E9%AB%98%E8%80%83%E5%BF%97%E6%84%BF%E6%8C%87%E5%8D%97",
      "hot": ""
    },
    {
      "rank": 8,
      "title": "日本 就怕邻居开路虎",
      "url": "https://s.weibo.com/weibo?q=%E6%97%A5%E6%9C%AC%20%E5%B0%B1%E6%80%95%E9%82%BB%E5%B1%85%E5%BC%80%E8%B7%AF%E8%99%8E",
      "hot": ""
    },
    {
      "rank": 9,
      "title": "莫离女二出息了",
      "url": "https://s.weibo.com/weibo?q=%E8%8E%AB%E7%A6%BB%E5%A5%B3%E4%BA%8C%E5%87%BA%E6%81%AF%E4%BA%86",
      "hot": ""
    },
    {
      "rank": 10,
      "title": "爸爸不收红包是全国统一的吗",
      "url": "https://s.weibo.com/weibo?q=%E7%88%B8%E7%88%B8%E4%B8%8D%E6%94%B6%E7%BA%A2%E5%8C%85%E6%98%AF%E5%85%A8%E5%9B%BD%E7%BB%9F%E4%B8%80%E7%9A%84%E5%90%97",
      "hot": ""
    }
  ]
}
