{
  "source": "zhihu_daily",
  "title": "知乎日报",
  "updated_at": "2026-06-23T04:31:40+00:00",
  "fetch_ok": true,
  "items": [
    {
      "rank": 1,
      "title": "过去一百年间，有哪些生物明显进化了？",
      "url": "https://daily.zhihu.com/story/9790624",
      "hot": "作者 / 蜉蝣影"
    },
    {
      "rank": 2,
      "title": "全网都在刷「负鼠表情包」，这种突然爆火的动物在现实里究竟是什么？",
      "url": "https://daily.zhihu.com/story/9790597",
      "hot": "作者 / 犬君拌汪酱"
    },
    {
      "rank": 3,
      "title": "杜拉斯的《情人》之所以那么著名，关键原因是什么？",
      "url": "https://daily.zhihu.com/story/9790569",
      "hot": "作者 / 鞭临天下"
    },
    {
      "rank": 4,
      "title": "哪个文物让你被老祖宗的审美震惊到了？",
      "url": "https://daily.zhihu.com/story/9790536",
      "hot": "作者 / Jarvis Xie"
    },
    {
      "rank": 5,
      "title": "角速度为什么是个矢量？",
      "url": "https://daily.zhihu.com/story/9790490",
      "hot": "作者 / 太空僧"
    },
    {
      "rank": 6,
      "title": "有哪些小政权出土的逆天文物？",
      "url": "https://daily.zhihu.com/story/9790634",
      "hot": "ag獭 · 5 分钟阅读"
    },
    {
      "rank": 7,
      "title": "为何说银河系的中央是巨大的黑洞？",
      "url": "https://daily.zhihu.com/story/9790638",
      "hot": "Achatinidae · 4 分钟阅读"
    },
    {
      "rank": 8,
      "title": "瞎扯 · 如何正确地吐槽",
      "url": "https://daily.zhihu.com/story/9790647",
      "hot": "VOL.3929"
    }
  ]
}
